metricflow/__about__.py
metricflow/__init__.py
metricflow/py.typed
metricflow/data_table/__init__.py
metricflow/data_table/column_types.py
metricflow/data_table/mf_column.py
metricflow/data_table/mf_table.py
metricflow/dataflow/__init__.py
metricflow/dataflow/dataflow_plan.py
metricflow/dataflow/dataflow_plan_analyzer.py
metricflow/dataflow/dataflow_plan_visitor.py
metricflow/dataflow/builder/__init__.py
metricflow/dataflow/builder/aggregation_helper.py
metricflow/dataflow/builder/builder_cache.py
metricflow/dataflow/builder/dataflow_plan_builder.py
metricflow/dataflow/builder/node_evaluator.py
metricflow/dataflow/builder/partitions.py
metricflow/dataflow/builder/simple_metric_input_spec_properties.py
metricflow/dataflow/builder/source_node.py
metricflow/dataflow/builder/source_node_recipe.py
metricflow/dataflow/nodes/__init__.py
metricflow/dataflow/nodes/add_generated_uuid.py
metricflow/dataflow/nodes/aggregate_simple_metric_inputs.py
metricflow/dataflow/nodes/alias_specs.py
metricflow/dataflow/nodes/combine_aggregated_outputs.py
metricflow/dataflow/nodes/compute_metrics.py
metricflow/dataflow/nodes/constrain_time.py
metricflow/dataflow/nodes/filter_elements.py
metricflow/dataflow/nodes/join_conversion_events.py
metricflow/dataflow/nodes/join_over_time.py
metricflow/dataflow/nodes/join_to_base.py
metricflow/dataflow/nodes/join_to_custom_granularity.py
metricflow/dataflow/nodes/join_to_time_spine.py
metricflow/dataflow/nodes/metric_time_transform.py
metricflow/dataflow/nodes/min_max.py
metricflow/dataflow/nodes/offset_base_grain_by_custom_grain.py
metricflow/dataflow/nodes/offset_custom_granularity.py
metricflow/dataflow/nodes/order_by_limit.py
metricflow/dataflow/nodes/read_sql_source.py
metricflow/dataflow/nodes/semi_additive_join.py
metricflow/dataflow/nodes/where_filter.py
metricflow/dataflow/nodes/window_reaggregation_node.py
metricflow/dataflow/nodes/write_to_data_table.py
metricflow/dataflow/nodes/write_to_table.py
metricflow/dataflow/optimizer/__init__.py
metricflow-0.209.0.dist-info/METADATA
metricflow-0.209.0.dist-info/WHEEL
metricflow-0.209.0.dist-info/licenses/LICENSE
metricflow-0.209.0.dist-info/RECORD
