Metadata-Version: 2.4
Name: metricflow
Version: 0.209.0
Summary: Translates a simple metric definition into reusable SQL and executes it against the SQL engine of your choice.
Project-URL: Documentation, https://docs.getdbt.com/docs/build/about-metricflow
Project-URL: Source Code, https://github.com/dbt-labs/metricflow
Author: dbt Labs
License-Expression: Apache-2.0
License-File: LICENSE
Classifier: Development Status :: 4 - Beta
Classifier: Programming Language :: Python
Classifier: Programming Language :: Python :: 3.9
Classifier: Programming Language :: Python :: 3.10
Classifier: Programming Language :: Python :: 3.11
Classifier: Programming Language :: Python :: 3.12
Classifier: Programming Language :: Python :: Implementation :: CPython
Classifier: Programming Language :: Python :: Implementation :: PyPy
Requires-Python: <3.13,>=3.9
Requires-Dist: dbt-semantic-interfaces==0.9.4.dev0
Requires-Dist: graphviz<0.21,>=0.18.2
Requires-Dist: jinja2<3.7.0,>=3.1.6
Requires-Dist: more-itertools<11.0.0,>=10.0.0
Requires-Dist: pydantic<3.0,>=1.10.0
Requires-Dist: python-dateutil<2.10.0,>=2.9.0
Requires-Dist: rapidfuzz<4.0,>=3.0
Requires-Dist: tabulate>=0.8.9
Requires-Dist: typing-extensions<5.0,>=4.4
Provides-Extra: dev-env-requirements
Requires-Dist: black<24,>=23.3; extra == 'dev-env-requirements'
Requires-Dist: click>=8.1.6; extra == 'dev-env-requirements'
Requires-Dist: dbt-core<1.11.0,>=1.10.4; extra == 'dev-env-requirements'
Requires-Dist: dbt-duckdb<1.9.0,>=1.8.0; extra == 'dev-env-requirements'
Requires-Dist: duckdb!=1.2.1,<1.4.0; extra == 'dev-env-requirements'
Requires-Dist: halo<0.1.0,>=0.0.31; extra == 'dev-env-requirements'
Requires-Dist: httpx<0.25,>=0.24; extra == 'dev-env-requirements'
Requires-Dist: hypothesis<7,>=6.87; extra == 'dev-env-requirements'
Requires-Dist: isort<6,>=5.12; extra == 'dev-env-requirements'
Requires-Dist: mypy<1.8.0,>=1.7.0; extra == 'dev-env-requirements'
Requires-Dist: pre-commit<3.3.0,>=3.2.2; extra == 'dev-env-requirements'
Requires-Dist: pydantic<2,>=1.10; extra == 'dev-env-requirements'
Requires-Dist: pympler<=2.0,>=1.1; extra == 'dev-env-requirements'
Requires-Dist: pytest-mock<3.15.0,>=3.14.0; extra == 'dev-env-requirements'
Requires-Dist: pytest-xdist<3.7.0,>=3.6.0; extra == 'dev-env-requirements'
Requires-Dist: pytest<9.0.0,>=8.0.0; extra == 'dev-env-requirements'
Requires-Dist: pyyaml<7.0.0,>=6.0; extra == 'dev-env-requirements'
Requires-Dist: tabulate>=0.8.9; extra == 'dev-env-requirements'
Requires-Dist: termcolor<4.0,>=3.0; extra == 'dev-env-requirements'
Requires-Dist: types-jinja2<3,>=2.11; extra == 'dev-env-requirements'
Requires-Dist: types-jsonschema<5,>=4.17; extra == 'dev-env-requirements'
Requires-Dist: types-python-dateutil; extra == 'dev-env-requirements'
Requires-Dist: types-pyyaml; extra == 'dev-env-requirements'
Requires-Dist: types-tabulate; extra == 'dev-env-requirements'
Requires-Dist: update-checker<0.19.0,>=0.18.0; extra == 'dev-env-requirements'
